{
  "version": "1.0",
  "updated_at": "2025-09-09T20:31:58.9408965+01:00",
  "package_count": 0,
  "packages": {
    "example-rules": {
      "name": "example-rules",
      "description": "Package containing rules.mdc",
      "latest": "1.0.0",
      "updated_at": "2025-09-09T20:20:36.8219349+01:00"
    },
    "test-rules": {
      "name": "test-rules",
      "description": "Package containing .\\testrule.mdc",
      "latest": "1.0.0",
      "updated_at": "2025-09-09T20:30:00.9792322+01:00"
    },
    "test-rules2": {
      "name": "test-rules2",
      "description": "Package containing .\\testrule.mdc",
      "latest": "1.0.0",
      "updated_at": "2025-09-09T20:30:03.72197+01:00"
    },
    "test3": {
      "name": "test3",
      "description": "Package containing .\\testrule.mdc",
      "latest": "1.0.0",
      "updated_at": "2025-09-09T20:31:58.9408965+01:00"
    },
    "testrules": {
      "name": "testrules",
      "description": "Package containing .\\testrule.mdc",
      "latest": "1.0.0",
      "updated_at": "2025-09-09T20:21:35.5055529+01:00"
    }
  }
}